odoo/addons/bus_alt_connection/README.rst
odoo/addons/bus_alt_connection/__init__.py
odoo/addons/bus_alt_connection/__manifest__.py
odoo/addons/bus_alt_connection/i18n/bus_alt_connection.pot
odoo/addons/bus_alt_connection/models/__init__.py
odoo/addons/bus_alt_connection/models/bus.py
odoo/addons/bus_alt_connection/readme/CONFIGURE.rst
odoo/addons/bus_alt_connection/readme/CONTRIBUTORS.rst
odoo/addons/bus_alt_connection/readme/DESCRIPTION.rst
odoo/addons/bus_alt_connection/readme/INSTALL.rst
odoo/addons/bus_alt_connection/static/description/icon.png
odoo/addons/bus_alt_connection/static/description/index.html
odoo12_addon_bus_alt_connection-12.0.1.0.0.99.dev2.dist-info/METADATA
odoo12_addon_bus_alt_connection-12.0.1.0.0.99.dev2.dist-info/WHEEL
odoo12_addon_bus_alt_connection-12.0.1.0.0.99.dev2.dist-info/top_level.txt
odoo12_addon_bus_alt_connection-12.0.1.0.0.99.dev2.dist-info/RECORD
